tomlval/__init__.py
tomlval/toml_schema.py
tomlval/toml_validator.py
tomlval/errors/__init__.py
tomlval/errors/toml_handler_error.py
tomlval/errors/toml_schema_error.py
tomlval/errors/toml_schema_key_error.py
tomlval/errors/toml_schema_merge_error.py
tomlval/types/__init__.py
tomlval/types/handler.py
tomlval/types/path_or_str.py
tomlval/utils/__init__.py
tomlval/utils/flatten.py
tomlval/utils/is_handler.py
tomlval/utils/is_toml.py
tomlval/utils/regex.py
tomlval/utils/stringify.py
tomlval/utils/to_path.py
tomlval/utils/unflatten.py
tomlval-1.1.5.dist-info/licenses/LICENSE
tomlval-1.1.5.dist-info/METADATA
tomlval-1.1.5.dist-info/WHEEL
tomlval-1.1.5.dist-info/top_level.txt
tomlval-1.1.5.dist-info/RECORD
