Metadata-Version: 2.4
Name: tomlval
Version: 1.1.5
Summary: A simple and easy to use TOML validator for Python.
Author-email: Marcus Fredriksson <marcus@marcusfredriksson.com>
License: MIT License
Project-URL: Homepage, https://github.com/marcusfrdk/tomlval
Project-URL: Repository, https://github.com/marcusfrdk/tomlval
Project-URL: Issues, https://github.com/marcusfrdk/tomlval/issues
Keywords: toml,validator,validation,python
Classifier: License :: OSI Approved :: MIT License
Classifier: Programming Language :: Python :: 3
Classifier: Operating System :: OS Independent
Requires-Python: >=3.11
License-File: LICENSE
Provides-Extra: build
Requires-Dist: build; extra == "build"
Requires-Dist: twine; extra == "build"
Provides-Extra: dev
Requires-Dist: black>=24.10.0; extra == "dev"
Requires-Dist: pytest>=8.3.4; extra == "dev"
Requires-Dist: isort>=5.13.2; extra == "dev"
Requires-Dist: pylint>=3.3.2; extra == "dev"
Requires-Dist: pre-commit>=4.0.1; extra == "dev"
Dynamic: license-file
